<?xml version="1.0" encoding="UTF-8" standalone="no" ?>
<operatorInstanceModel xmlns="http://www.ibm.com/xmlns/prod/streams/spl/operator/instance" xmlns:tt="http://www.ibm.com/xmlns/prod/streams/spl/tupleType" xmlns:xsi="http://www.w3.org/2001/XMLSchema-instance">

  <context>
    <kind>application::TwitterSource</kind>
    <class>TwitterSource_out</class>
    <operatorModelDirectory>/opt/ibm/InfoSphereStreams/toolkits/spl/spl/utility/JavaOp</operatorModelDirectory>
    <applicationDirectory>/home/stradmin/labs/twitter-piotr/twitter-demo</applicationDirectory>
    <dataDirectory>/home/stradmin/labs/twitter-piotr/twitter-demo/data</dataDirectory>
    <outputDirectory>/home/stradmin/labs/twitter-piotr/twitter-demo/output/application.twitterdemo/Distributed</outputDirectory>
    <optimized>false</optimized>
    <verbose>false</verbose>
    <networkByteOrdering>false</networkByteOrdering>
    <codeBeautification>false</codeBeautification>
    <includes>
      <include>"../type/BeJwrMSk2KS1OLSo2yUnMS88pMs9ILM4oSUwvNilJrSgBALIkAu5.h"</include>
    </includes>
    <stateVariables/>
    <runtimeConstants>
      <runtimeConstant>
        <name>lit$0</name>
        <cppType>SPL::rstring</cppType>
        <splType>rstring</splType>
        <value>"$TWTR"</value>
      </runtimeConstant>
    </runtimeConstants>
    <sourceLocation>
      <file>application/twitterdemo.spl</file>
      <line>6</line>
      <column>3</column>
    </sourceLocation>
    <productVersion>3.1.0.0</productVersion>
    <javaOperatorModelDirectory>application/TwitterSource</javaOperatorModelDirectory>
    <checkpointKind>none</checkpointKind>
  </context>

  <parameters>
    <parameter>
      <name>className</name>
      <values>
        <value>
          <cppType>SPL::rstring</cppType>
          <splType>rstring</splType>
          <hasRuntimeConstant>false</hasRuntimeConstant>
          <cppExpression>SPL::rstring("application.TwitterSource")</cppExpression>
          <splExpression>"application.TwitterSource"</splExpression>
          <hasFunctions>false</hasFunctions>
          <hasSideEffects>false</hasSideEffects>
          <hasStreamAttributes>false</hasStreamAttributes>
          <parameterExpressionMode>AttributeFree</parameterExpressionMode>
          <sourceLocation>
            <file>&lt;invalid&gt;</file>
            <line>-1</line>
            <column>0</column>
          </sourceLocation>
        </value>
      </values>
      <sourceLocation>
        <file>&lt;invalid&gt;</file>
        <line>-1</line>
        <column>0</column>
      </sourceLocation>
    </parameter>
    <parameter>
      <name>classLibrary</name>
      <values>
        <value>
          <cppType>SPL::rstring</cppType>
          <splType>rstring</splType>
          <hasRuntimeConstant>false</hasRuntimeConstant>
          <cppExpression>SPL::rstring("../../../impl/java/bin")</cppExpression>
          <splExpression>"../../../impl/java/bin"</splExpression>
          <hasFunctions>false</hasFunctions>
          <hasSideEffects>false</hasSideEffects>
          <hasStreamAttributes>false</hasStreamAttributes>
          <parameterExpressionMode>AttributeFree</parameterExpressionMode>
          <sourceLocation>
            <file>&lt;invalid&gt;</file>
            <line>-1</line>
            <column>0</column>
          </sourceLocation>
        </value>
        <value>
          <cppType>SPL::rstring</cppType>
          <splType>rstring</splType>
          <hasRuntimeConstant>false</hasRuntimeConstant>
          <cppExpression>SPL::rstring("../../../impl/lib/twitter4j-async-4.0.1.jar")</cppExpression>
          <splExpression>"../../../impl/lib/twitter4j-async-4.0.1.jar"</splExpression>
          <hasFunctions>false</hasFunctions>
          <hasSideEffects>false</hasSideEffects>
          <hasStreamAttributes>false</hasStreamAttributes>
          <parameterExpressionMode>AttributeFree</parameterExpressionMode>
          <sourceLocation>
            <file>&lt;invalid&gt;</file>
            <line>-1</line>
            <column>0</column>
          </sourceLocation>
        </value>
        <value>
          <cppType>SPL::rstring</cppType>
          <splType>rstring</splType>
          <hasRuntimeConstant>false</hasRuntimeConstant>
          <cppExpression>SPL::rstring("../../../impl/lib/twitter4j-core-4.0.1.jar")</cppExpression>
          <splExpression>"../../../impl/lib/twitter4j-core-4.0.1.jar"</splExpression>
          <hasFunctions>false</hasFunctions>
          <hasSideEffects>false</hasSideEffects>
          <hasStreamAttributes>false</hasStreamAttributes>
          <parameterExpressionMode>AttributeFree</parameterExpressionMode>
          <sourceLocation>
            <file>&lt;invalid&gt;</file>
            <line>-1</line>
            <column>0</column>
          </sourceLocation>
        </value>
        <value>
          <cppType>SPL::rstring</cppType>
          <splType>rstring</splType>
          <hasRuntimeConstant>false</hasRuntimeConstant>
          <cppExpression>SPL::rstring("../../../impl/lib/twitter4j-stream-4.0.1.jar")</cppExpression>
          <splExpression>"../../../impl/lib/twitter4j-stream-4.0.1.jar"</splExpression>
          <hasFunctions>false</hasFunctions>
          <hasSideEffects>false</hasSideEffects>
          <hasStreamAttributes>false</hasStreamAttributes>
          <parameterExpressionMode>AttributeFree</parameterExpressionMode>
          <sourceLocation>
            <file>&lt;invalid&gt;</file>
            <line>-1</line>
            <column>0</column>
          </sourceLocation>
        </value>
      </values>
      <sourceLocation>
        <file>&lt;invalid&gt;</file>
        <line>-1</line>
        <column>0</column>
      </sourceLocation>
    </parameter>
    <parameter>
      <name>filter</name>
      <values>
        <value>
          <cppType>SPL::rstring</cppType>
          <splType>rstring</splType>
          <hasRuntimeConstant>true</hasRuntimeConstant>
          <cppExpression>lit$0</cppExpression>
          <splExpression>"$TWTR"</splExpression>
          <hasFunctions>false</hasFunctions>
          <hasSideEffects>false</hasSideEffects>
          <hasStreamAttributes>false</hasStreamAttributes>
          <parameterExpressionMode>AttributeFree</parameterExpressionMode>
          <sourceLocation>
            <file>application/twitterdemo.spl</file>
            <line>9</line>
            <column>14</column>
          </sourceLocation>
        </value>
      </values>
      <sourceLocation>
        <file>application/twitterdemo.spl</file>
        <line>9</line>
        <column>5</column>
      </sourceLocation>
    </parameter>
  </parameters>

  <inputPorts/>

  <outputPorts>
    <outputPort>
      <index>0</index>
      <tupleCppName>oport$0</tupleCppName>
      <tupleCppType>SPL::BeJwrMSk2KS1OLSo2yUnMS88pMs9ILM4oSUwvNilJrSgBALIkAu5</tupleCppType>
      <tupleSPLType>tuple&lt;rstring user,rstring lang,list&lt;ustring&gt; hashtag,rstring text&gt;</tupleSPLType>
      <facade>false</facade>
      <mutationAllowed>true</mutationAllowed>
      <sourceLocation>
        <file>application/twitterdemo.spl</file>
        <line>6</line>
        <column>3</column>
      </sourceLocation>
      <attributes>
        <attribute>
          <name>user</name>
          <cppType>SPL::rstring</cppType>
          <splType>rstring</splType>
        </attribute>
        <attribute>
          <name>lang</name>
          <cppType>SPL::rstring</cppType>
          <splType>rstring</splType>
        </attribute>
        <attribute>
          <name>hashtag</name>
          <cppType>SPL::list&lt;SPL::ustring &gt;</cppType>
          <splType>list&lt;ustring&gt;</splType>
        </attribute>
        <attribute>
          <name>text</name>
          <cppType>SPL::rstring</cppType>
          <splType>rstring</splType>
        </attribute>
      </attributes>
      <tuple>
        <tt:attr name="user" type="rstring"/>
        <tt:attr name="lang" type="rstring"/>
        <tt:attr name="hashtag">
          <tt:list elementType="ustring"/>
        </tt:attr>
        <tt:attr name="text" type="rstring"/>
      </tuple>
      <finalPunctuationPortScope/>
    </outputPort>
  </outputPorts>

</operatorInstanceModel>
